tiledbsoma/__init__.py
tiledbsoma/_arrow_types.py
tiledbsoma/_collection.py
tiledbsoma/_common_nd_array.py
tiledbsoma/_constants.py
tiledbsoma/_coordinate_selection.py
tiledbsoma/_dataframe.py
tiledbsoma/_dense_nd_array.py
tiledbsoma/_eager_iter.py
tiledbsoma/_exception.py
tiledbsoma/_experiment.py
tiledbsoma/_factory.py
tiledbsoma/_fastercsx.py
tiledbsoma/_funcs.py
tiledbsoma/_general_utilities.py
tiledbsoma/_geometry_dataframe.py
tiledbsoma/_indexer.py
tiledbsoma/_managed_query.py
tiledbsoma/_measurement.py
tiledbsoma/_multiscale_image.py
tiledbsoma/_point_cloud_dataframe.py
tiledbsoma/_query.py
tiledbsoma/_query_condition.py
tiledbsoma/_read_iters.py
tiledbsoma/_scene.py
tiledbsoma/_soma_array.py
tiledbsoma/_soma_group.py
tiledbsoma/_soma_object.py
tiledbsoma/_sparse_nd_array.py
tiledbsoma/_spatial_dataframe.py
tiledbsoma/_spatial_util.py
tiledbsoma/_tdb_handles.py
tiledbsoma/_types.py
tiledbsoma/_util.py
tiledbsoma/eta.py
tiledbsoma/experiment_query.py
tiledbsoma/libtiledbsoma.so
tiledbsoma/logging.py
tiledbsoma/py.typed
tiledbsoma/pytiledbsoma.cpython-39-x86_64-linux-gnu.so
tiledbsoma/stats.py
tiledbsoma/_dask/__init__.py
tiledbsoma/_dask/load.py
tiledbsoma/_dask/util.py
tiledbsoma/io/__init__.py
tiledbsoma/io/_caching_reader.py
tiledbsoma/io/_common.py
tiledbsoma/io/_util.py
tiledbsoma/io/conversions.py
tiledbsoma/io/ingest.py
tiledbsoma/io/outgest.py
tiledbsoma/io/shaping.py
tiledbsoma/io/update_uns.py
tiledbsoma/io/_registration/__init__.py
tiledbsoma/io/_registration/ambient_label_mappings.py
tiledbsoma/io/_registration/enum.py
tiledbsoma/io/_registration/id_mappings.py
tiledbsoma/io/spatial/__init__.py
tiledbsoma/io/spatial/_spatialdata_util.py
tiledbsoma/io/spatial/_util.py
tiledbsoma/io/spatial/_xarray_backend.py
tiledbsoma/io/spatial/ingest.py
tiledbsoma/io/spatial/outgest.py
tiledbsoma/options/__init__.py
tiledbsoma/options/_soma_tiledb_context.py
tiledbsoma-2.2.0.dist-info/METADATA
tiledbsoma-2.2.0.dist-info/WHEEL
tiledbsoma-2.2.0.dist-info/top_level.txt
tiledbsoma-2.2.0.dist-info/RECORD
