Metadata-Version: 2.4
Name: tiledbsoma
Version: 2.2.0
Summary: Python API for efficient storage and retrieval of single-cell data using TileDB
Home-page: https://github.com/single-cell-data/TileDB-SOMA/tree/main/apis/python
Author: TileDB, Inc.
Author-email: help@tiledb.io
Maintainer: TileDB, Inc.
Maintainer-email: help@tiledb.io
License: MIT
Classifier: Intended Audience :: Developers
Classifier: Intended Audience :: Information Technology
Classifier: Intended Audience :: Science/Research
Classifier: Topic :: Scientific/Engineering :: Bio-Informatics
Classifier: Operating System :: Unix
Classifier: Operating System :: POSIX :: Linux
Classifier: Operating System :: MacOS :: MacOS X
Classifier: Operating System :: Microsoft :: Windows
Classifier: Programming Language :: Python
Classifier: Programming Language :: Python :: 3.9
Classifier: Programming Language :: Python :: 3.10
Classifier: Programming Language :: Python :: 3.11
Classifier: Programming Language :: Python :: 3.12
Classifier: Programming Language :: Python :: 3.13
Requires-Python: >=3.9
Requires-Dist: anndata>=0.10.1
Requires-Dist: attrs>=22.2
Requires-Dist: more-itertools
Requires-Dist: numpy
Requires-Dist: pandas
Requires-Dist: pyarrow
Requires-Dist: scanpy>=1.9.2
Requires-Dist: scipy
Requires-Dist: somacore==1.0.29
Requires-Dist: typing-extensions>=4.5.0
Provides-Extra: dev
Requires-Dist: black; extra == "dev"
Requires-Dist: dask; extra == "dev"
Requires-Dist: pytest; extra == "dev"
Requires-Dist: pytest-cov; extra == "dev"
Requires-Dist: ruff; extra == "dev"
Requires-Dist: sparse; extra == "dev"
Requires-Dist: typeguard==4.4.2; extra == "dev"
Requires-Dist: types-setuptools; extra == "dev"
Requires-Dist: more-itertools; extra == "dev"
Requires-Dist: hypothesis; extra == "dev"
Requires-Dist: deepdiff; extra == "dev"
Provides-Extra: spatial-io
Requires-Dist: geopandas; extra == "spatial-io"
Requires-Dist: tifffile; extra == "spatial-io"
Requires-Dist: pillow; extra == "spatial-io"
Requires-Dist: spatialdata>=0.2.5; extra == "spatial-io"
Requires-Dist: xarray; extra == "spatial-io"
Requires-Dist: dask; extra == "spatial-io"
Provides-Extra: all
Requires-Dist: black; extra == "all"
Requires-Dist: dask; extra == "all"
Requires-Dist: pytest; extra == "all"
Requires-Dist: pytest-cov; extra == "all"
Requires-Dist: ruff; extra == "all"
Requires-Dist: sparse; extra == "all"
Requires-Dist: typeguard==4.4.2; extra == "all"
Requires-Dist: types-setuptools; extra == "all"
Requires-Dist: more-itertools; extra == "all"
Requires-Dist: hypothesis; extra == "all"
Requires-Dist: deepdiff; extra == "all"
Requires-Dist: geopandas; extra == "all"
Requires-Dist: tifffile; extra == "all"
Requires-Dist: pillow; extra == "all"
Requires-Dist: spatialdata>=0.2.5; extra == "all"
Requires-Dist: xarray; extra == "all"
Requires-Dist: dask; extra == "all"
Dynamic: author
Dynamic: author-email
Dynamic: classifier
Dynamic: description
Dynamic: description-content-type
Dynamic: home-page
Dynamic: license
Dynamic: maintainer
Dynamic: maintainer-email
Dynamic: provides-extra
Dynamic: requires-dist
Dynamic: requires-python
Dynamic: summary
